<?xml version="1.0" encoding="utf-8" ?>
<c2layout>
    <name>Level</name>
    <sid>8873350371196689</sid>
    <event-sheet>Event sheet 1</event-sheet>
    <size>
        <width>3840</width>
        <height>2160</height>
    </size>
    <margins>
        <horizontal>500</horizontal>
        <vertical>500</vertical>
    </margins>
    <unbounded-scrolling>0</unbounded-scrolling>
    <layers>
        <layer name="Layer 0" sid="8722530541249526">
            <initially-visible>1</initially-visible>
            <background-color>255,255,255</background-color>
            <transparent>0</transparent>
            <parallax>
                <x>1</x>
                <y>1</y>
            </parallax>
            <zoom-rate>1</zoom-rate>
            <opacity>1</opacity>
            <force-own-texture>0</force-own-texture>
            <global>0</global>
            <use-render-cells>0</use-render-cells>
            <blend-mode>0</blend-mode>
            <effect-fallback>0</effect-fallback>
            <instances>
                <instance type="Sprite" uid="0">
                    <properties>
                        <initial-visibility>Visible</initial-visibility>
                        <initial-animation>Default</initial-animation>
                        <initial-frame>0</initial-frame>
                        <collisions>Enabled</collisions>
                    </properties>
                    <behavior-instances>
                        <behavior-instance type="Platform">
                            <properties>
                                <max-speed>330</max-speed>
                                <acceleration>1500</acceleration>
                                <deceleration>1500</deceleration>
                                <jump-strength>1000</jump-strength>
                                <gravity>1500</gravity>
                                <max-fall-speed>1000</max-fall-speed>
                                <double-jump>Disabled</double-jump>
                                <jump-sustain>0</jump-sustain>
                                <default-controls>Yes</default-controls>
                                <initial-state>Enabled</initial-state>
                            </properties>
                        </behavior-instance>
                    </behavior-instances>
                    <blend-mode>0</blend-mode>
                    <effect-fallback>0</effect-fallback>
                    <world>
                        <x>1247</x>
                        <y>1554</y>
                        <z>0</z>
                        <width>669</width>
                        <height>569</height>
                        <depth>0</depth>
                        <hotspotX>0.500747383</hotspotX>
                        <hotspotY>0.500878751</hotspotY>
                        <angle>0</angle>
                        <opacity>1</opacity>
                    </world>
                </instance>
                <instance type="Sprite2" uid="1">
                    <properties>
                        <initial-visibility>Visible</initial-visibility>
                        <initial-animation>Default</initial-animation>
                        <initial-frame>0</initial-frame>
                        <collisions>Enabled</collisions>
                    </properties>
                    <behavior-instances>
                        <behavior-instance type="Solid">
                            <properties>
                                <initial-state>Enabled</initial-state>
                            </properties>
                        </behavior-instance>
                    </behavior-instances>
                    <blend-mode>0</blend-mode>
                    <effect-fallback>0</effect-fallback>
                    <world>
                        <x>1939.407958984</x>
                        <y>1788</y>
                        <z>0</z>
                        <width>3867</width>
                        <height>119</height>
                        <depth>0</depth>
                        <hotspotX>0.5</hotspotX>
                        <hotspotY>0.5</hotspotY>
                        <angle>0</angle>
                        <opacity>1</opacity>
                    </world>
                </instance>
            </instances>
            <effects />
        </layer>
    </layers>
    <nonworld-instances />
    <effects />
</c2layout>
